{
    "unknown": {
        "unk_12": 2, 
        "unk_4": 0, 
        "unk_5": 0, 
        "unk_6": 0, 
        "unk_7": 0
    }, 
    "objective_details": {
        "subquest_2": {
            "objective_num": 0, 
            "hrp_reward": 0, 
            "rewards_row_1": [], 
            "description": "None", 
            "objective_type": 0, 
            "zenny_reward": 0, 
            "type": 0
        }, 
        "main_quest": {
            "objective_num": 1, 
            "hrp_reward": 1760, 
            "rewards_row_1": [
                [
                    479, 
                    1, 
                    1
                ], 
                [
                    457, 
                    1, 
                    14
                ], 
                [
                    410, 
                    1, 
                    10
                ], 
                [
                    296, 
                    1, 
                    20
                ], 
                [
                    386, 
                    1, 
                    12
                ], 
                [
                    455, 
                    8, 
                    9
                ], 
                [
                    412, 
                    1, 
                    9
                ], 
                [
                    592, 
                    1, 
                    25
                ]
            ], 
            "rewards_row_2": [
                [
                    479, 
                    1, 
                    1
                ], 
                [
                    457, 
                    1, 
                    14
                ], 
                [
                    410, 
                    1, 
                    10
                ], 
                [
                    296, 
                    1, 
                    20
                ], 
                [
                    386, 
                    1, 
                    12
                ], 
                [
                    455, 
                    1, 
                    9
                ], 
                [
                    412, 
                    1, 
                    9
                ], 
                [
                    592, 
                    1, 
                    25
                ]
            ], 
            "objective_type": 9, 
            "zenny_reward": 17600, 
            "type": 1
        }, 
        "subquest_1": {
            "objective_num": 1, 
            "hrp_reward": 0, 
            "rewards_row_1": [], 
            "description": "None", 
            "objective_type": 6, 
            "zenny_reward": 0, 
            "type": 1
        }
    }, 
    "small_monsters": [
        [], 
        [
            {
                "variant": 3, 
                "unk1": 1, 
                "unk2": 255, 
                "pos_z": -3542.7, 
                "pos_x": -2404.5, 
                "pos_y": -5038.5, 
                "room": 1, 
                "rot_z": 0, 
                "rot_y": 170, 
                "rot_x": 0, 
                "type": 40, 
                "quantity": -1
            }
        ]
    ], 
    "quest_info": {
        "wave_1_transition_type": 0, 
        "time_limit": 50, 
        "wave_1_transition_quantity": 0, 
        "starting_position": 0, 
        "quest_rank": 3, 
        "wave_2_transition_target": 0, 
        "wave_2_transition_quantity": 0, 
        "general_enemy_level": 29, 
        "wave_2_transition_type": 0, 
        "location": 8, 
        "penalty_per_cart": 6000, 
        "resources": 0, 
        "details": "Oh, boo! I'm tired of watching\nrun-of-the-mill hunts. The\nDiablos and the Uragaan are\nsupposed to be the ultimate\nmonster duo. I'd love to watch\nthem maim some foolish hunter!\nDo put on a good show...", 
        "description": "Hunt an Uragaan\nand a Diablos", 
        "wave_1_transition_target": 0, 
        "hrp_restriction": 8, 
        "quest_fee": 1750, 
        "quest_id": 61008, 
        "name": "Blood Sport", 
        "main_monster_2": 6, 
        "main_monster_1": 9, 
        "supply_set_number": 43, 
        "summon": 0, 
        "client": "Spoiled Princess", 
        "flags": [
            [
                0, 
                1, 
                0, 
                0, 
                0, 
                0, 
                0, 
                0
            ], 
            [
                1, 
                1, 
                0, 
                0, 
                0, 
                0, 
                0, 
                0
            ], 
            [
                0, 
                0, 
                0, 
                0, 
                0, 
                0, 
                0, 
                0
            ], 
            [
                1, 
                0, 
                1, 
                0, 
                0, 
                0, 
                0, 
                0
            ]
        ], 
        "success_message": "Complete the Main Quest."
    }, 
    "large_monsters": {
        "monster_2": {
            "size_spread": 3, 
            "hp_spread": 1, 
            "level": 29, 
            "boss_id": 1, 
            "type": 6, 
            "starting_area": 0, 
            "spawn_count": 1, 
            "size": 100
        }, 
        "monster_3": {
            "size_spread": 0, 
            "hp_spread": 0, 
            "level": 0, 
            "boss_id": 0, 
            "type": 0, 
            "starting_area": 0, 
            "spawn_count": 0, 
            "size": 0
        }, 
        "monster_1": {
            "size_spread": 3, 
            "hp_spread": 1, 
            "level": 29, 
            "boss_id": 0, 
            "type": 9, 
            "starting_area": 0, 
            "spawn_count": 1, 
            "size": 100
        }
    }
}